wowp/__about__.py
wowp/__init__.py
wowp/components.py
wowp/logger.py
wowp/schedulers.py
wowp/util.py
wowp/actors/__init__.py
wowp/actors/base.py
wowp/actors/experimental.py
wowp/actors/julia.py
wowp/actors/mapreduce.py
wowp/actors/matlab_actors.py
wowp/actors/omfit.py
wowp/actors/special.py
wowp/tools/__init__.py
wowp/tools/plotting.py
wowp-0.3.0.data/scripts/wowp
wowp-0.3.0.data/scripts/wowp_on_slurm
wowp-0.3.0.dist-info/LICENSE.txt
wowp-0.3.0.dist-info/METADATA
wowp-0.3.0.dist-info/WHEEL
wowp-0.3.0.dist-info/top_level.txt
wowp-0.3.0.dist-info/RECORD
