Metadata-Version: 2.1
Name: wowp
Version: 0.3.0
Summary: Data-flow-actors-based workflow framework
Home-page: http://pythonic.eu/wowp/
Author: Jakub Urban, Jan Pipek
Author-email: coobas@gmail.com
License: MIT
Platform: UNKNOWN
Classifier: Programming Language :: Python :: 2.7
Classifier: Programming Language :: Python :: 3.4
Classifier: Programming Language :: Python :: 3.5
Classifier: Development Status :: 3 - Alpha
Classifier: License :: OSI Approved :: MIT License
Classifier: Operating System :: OS Independent
Classifier: Intended Audience :: Developers
Classifier: Intended Audience :: Information Technology
Classifier: Intended Audience :: Science/Research
Classifier: Topic :: Scientific/Engineering
Classifier: Topic :: Software Development :: Libraries :: Python Modules
Requires-Dist: decorator
Requires-Dist: future
Requires-Dist: networkx
Requires-Dist: nose
Requires-Dist: six
Requires-Dist: click
Provides-Extra: all
Requires-Dist: ipyparallel; extra == 'all'
Requires-Dist: mpi4py; extra == 'all'
Requires-Dist: distributed; extra == 'all'
Requires-Dist: julia; extra == 'all'
Requires-Dist: matlab; extra == 'all'
Requires-Dist: stopit; extra == 'all'
Provides-Extra: distributed
Requires-Dist: distributed; extra == 'distributed'
Provides-Extra: julia
Requires-Dist: julia; extra == 'julia'
Provides-Extra: matlab
Requires-Dist: matlab; extra == 'matlab'
Requires-Dist: stopit; extra == 'matlab'
Provides-Extra: parallel
Requires-Dist: ipyparallel; extra == 'parallel'
Requires-Dist: mpi4py; extra == 'parallel'
